topsis/__init__.py
topsis/__main__.py
Topsis_Meghna_102003663-0.0.0.dist-info/LICENSE
Topsis_Meghna_102003663-0.0.0.dist-info/METADATA
Topsis_Meghna_102003663-0.0.0.dist-info/WHEEL
Topsis_Meghna_102003663-0.0.0.dist-info/entry_points.txt
Topsis_Meghna_102003663-0.0.0.dist-info/top_level.txt
Topsis_Meghna_102003663-0.0.0.dist-info/RECORD
