Metadata-Version: 2.1
Name: Topsis_Meghna_102003663
Version: 0.0.0
Summary: Topsis Implementation
Home-page: https://github.com/meghna3107/Topsis-meghna-102003663.git
Author: meghna
Author-email: mmeghna_be20@thapar.edu
License: MIT
Classifier: License :: OSI Approved :: MIT License
Classifier: Programming Language :: Python :: 3.6
Classifier: Programming Language :: Python :: 3.7
Classifier: Programming Language :: Python :: 3.8
License-File: LICENSE
